{
  "setup": [
    {
      "variant": "m",
      "requiredArea": {
        "min": 80000,
        "max": 120000
      },
      "type": "wcBathroom"
    },
    {
      "variant": "s",
      "requiredArea": {
        "min": 50000,
        "max": 90000
      },
      "type": "wcBathroom"
    },
    {
      "variant": "m",
      "requiredArea": {
        "min": 100000,
        "max": 120000
      },
      "type": "bedroom"
    },
    {
      "variant": "m",
      "requiredArea": {
        "min": 100000,
        "max": 120000
      },
      "type": "bedroom"
    },
    {
      "variant": "m",
      "requiredArea": {
        "min": 360000,
        "max": 440000
      },
      "type": "livingKitchen"
    },
    {
      "type": "entrance",
      "variant": "m",
      "requiredArea": {
        "min": 25000,
        "max": 50000
      }
    }
  ]
}