{
  "setup": [
    {
      "type": "entrance",
      "variant": "m",
      "requiredArea": {
        "min": 25000,
        "max": 60000
      }
    },
    {
      "variant": "m",
      "requiredArea": {
        "min": 60000,
        "max": 80000
      },
      "type": "bathroom"
    },
    {
      "variant": "s",
      "requiredArea": {
        "min": 10000,
        "max": 30000
      },
      "type": "wc"
    },
    {
      "variant": "s",
      "requiredArea": {
        "min": 90000,
        "max": 100000
      },
      "type": "bedroom"
    },
    {
      "variant": "m",
      "requiredArea": {
        "min": 100000,
        "max": 120000
      },
      "type": "bedroom"
    },
    {
      "variant": "m",
      "requiredArea": {
        "min": 100000,
        "max": 120000
      },
      "type": "bedroom"
    },
    {
      "variant": "l",
      "requiredArea": {
        "min": 130000,
        "max": 150000
      },
      "type": "bedroom"
    },
    {
      "variant": "m",
      "requiredArea": {
        "min": 360000,
        "max": 440000
      },
      "type": "livingKitchen"
    }
  ]
}