{
  "meta": {
    "cacheKey": "LT02_0",
    "projectSlug": "test-base",
    "slug": "LT02"
  },
  "v1": {
    "apartment": {
      "area": 828564,
      "blueprints": [
        {
          "externalSpaces": [
            {
              "area": 31184.043157861466,
              "polygon": [
                [
                  1421.5676098776914,
                  -560.8928296285046
                ],
                [
                  1358.42021989888,
                  -436.09081827082827
                ],
                [
                  1061.991123916672,
                  -585.450122668961
                ],
                [
                  1125.1529282552888,
                  -710.2806219991401
                ]
              ],
              "type": "terrace",
              "windows": [
                4,
                5
              ]
            }
          ],
          "externalWalls": [
            0,
            1,
            2,
            3,
            4,
            5,
            6,
            7,
            8
          ],
          "fixedItems": [
            {
              "coef1": 84,
              "coef2": 403,
              "sillHeight": 0,
              "type": "doorWindow",
              "vertex1": 1,
              "vertex2": 2,
              "width": 80
            },
            {
              "coef1": 544,
              "coef2": 863,
              "sillHeight": 0,
              "type": "doorWindow",
              "vertex1": 1,
              "vertex2": 2,
              "width": 80
            },
            {
              "coef1": 140,
              "coef2": 465,
              "sillHeight": 0,
              "type": "doorWindow",
              "vertex1": 7,
              "vertex2": 8,
              "width": 80
            },
            {
              "coef1": 592,
              "coef2": 917,
              "sillHeight": 0,
              "type": "doorWindow",
              "vertex1": 7,
              "vertex2": 8,
              "width": 80
            },
            {
              "coef1": 213,
              "coef2": 1000,
              "sillHeight": 0,
              "type": "doorWindow",
              "vertex1": 6,
              "vertex2": 7,
              "width": 80
            },
            {
              "coef1": 28,
              "coef2": 898,
              "sillHeight": 0,
              "type": "doorWindow",
              "vertex1": 5,
              "vertex2": 6,
              "width": 80
            },
            {
              "coef1": 590,
              "coef2": 701,
              "type": "frontDoor",
              "vertex1": 2,
              "vertex2": 3,
              "width": 90
            },
            {
              "coef1": 442,
              "coef2": 557,
              "type": "duct",
              "vertex1": 9,
              "vertex2": 10,
              "width": 65
            },
            {
              "coef1": 354,
              "coef2": 441,
              "type": "duct",
              "vertex1": 9,
              "vertex2": 10,
              "width": -45
            },
            {
              "coef1": 49,
              "coef2": 280,
              "type": "duct",
              "vertex1": 11,
              "vertex2": 12,
              "width": -70
            }
          ],
          "forbiddenZones": [],
          "level": 1,
          "loadBearingWalls": [
            [
              9,
              10
            ],
            [
              11,
              12
            ]
          ],
          "rooms": [],
          "unsplittableZones": [],
          "vertices": [
            {
              "x": 1605,
              "y": 426
            },
            {
              "x": 1411,
              "y": 811
            },
            {
              "x": 859,
              "y": 533
            },
            {
              "x": 1255,
              "y": -252
            },
            {
              "x": 958,
              "y": -402
            },
            {
              "x": 1053,
              "y": -590
            },
            {
              "x": 1358,
              "y": -436
            },
            {
              "x": 1422,
              "y": -561
            },
            {
              "x": 1964,
              "y": -287
            },
            {
              "x": 1726,
              "y": -409
            },
            {
              "x": 1171,
              "y": 691
            },
            {
              "x": 1381,
              "y": 300
            },
            {
              "x": 1611,
              "y": 416
            }
          ]
        }
      ],
      "id": "LT02",
      "ifcIds": [
        73358,
        100090,
        108386
      ],
      "levels": [
        1
      ],
      "north": [
        0.0,
        1.0
      ]
    }
  },
  "v2": {
    "aptInfos": {
      "north": [
        0.0,
        1.0
      ]
    },
    "floors": [
      {
        "elements": [
          301,
          201,
          202,
          203,
          204,
          205,
          206,
          207,
          302,
          303,
          304,
          305,
          306,
          307
        ],
        "id": 401,
        "level": 1
      }
    ],
    "linears": [
      {
        "category": "doorWindow",
        "externalSpaces": [
          302,
          302
        ],
        "geometry": [
          1010,
          1011
        ],
        "id": 201,
        "length": 197.09174153003863,
        "sillHeight": 0
      },
      {
        "category": "doorWindow",
        "externalSpaces": [],
        "geometry": [
          1012,
          1013
        ],
        "id": 202,
        "length": 197.09174153000245,
        "sillHeight": 0
      },
      {
        "category": "doorWindow",
        "externalSpaces": [],
        "geometry": [
          1014,
          1015
        ],
        "id": 203,
        "length": 197.09174153006373,
        "sillHeight": 0
      },
      {
        "category": "doorWindow",
        "externalSpaces": [],
        "geometry": [
          1016,
          1017
        ],
        "id": 204,
        "length": 197.0917415300201,
        "sillHeight": 0
      },
      {
        "category": "doorWindow",
        "externalSpaces": [],
        "geometry": [
          1018,
          1019
        ],
        "id": 205,
        "length": 110.04304535958359,
        "sillHeight": 0
      },
      {
        "category": "doorWindow",
        "externalSpaces": [],
        "geometry": [
          1020,
          1021
        ],
        "id": 206,
        "length": 297.37445012998813,
        "sillHeight": 0
      },
      {
        "category": "frontDoor",
        "geometry": [
          1022,
          1023
        ],
        "id": 207,
        "length": 96.99964547380024
      }
    ],
    "spaces": [
      {
        "area": 828563.8015809011,
        "category": "empty",
        "geometry": [
          101,
          102,
          103,
          104,
          105,
          106,
          107,
          108,
          109
        ],
        "id": 301
      },
      {
        "area": 3118404.3157861466,
        "category": "terrace",
        "geometry": [
          1024,
          1025,
          1026,
          1027
        ],
        "id": 302
      },
      {
        "area": 30750.768393755956,
        "category": "loadBearingWall",
        "geometry": [
          1028,
          1029,
          1030,
          1031
        ],
        "id": 303
      },
      {
        "area": 6377.935936482824,
        "category": "loadBearingWall",
        "geometry": [
          1032,
          1033,
          1034,
          1035
        ],
        "id": 304
      },
      {
        "area": 6612.000173178139,
        "category": "duct",
        "geometry": [
          1036,
          1037,
          1038,
          1039,
          1040,
          1041
        ],
        "id": 305
      },
      {
        "area": 4813.910903060997,
        "category": "duct",
        "geometry": [
          1042,
          1043,
          1044,
          1045
        ],
        "id": 306
      },
      {
        "area": 4901.21827937348,
        "category": "duct",
        "geometry": [
          1046,
          1047,
          1048,
          1049
        ],
        "id": 307
      }
    ],
    "vertices": [
      {
        "id": 101,
        "x": 1604.5462339427281,
        "y": 426.40494747519205
      },
      {
        "id": 102,
        "x": 1410.6154175500008,
        "y": 811.0012678460001
      },
      {
        "id": 103,
        "x": 859.1092724750002,
        "y": 533.0518700609999
      },
      {
        "id": 104,
        "x": 1254.709014220378,
        "y": -251.89478399971614
      },
      {
        "id": 105,
        "x": 957.786493990225,
        "y": -401.5385181058444
      },
      {
        "id": 106,
        "x": 1053.015520502085,
        "y": -589.8606099215176
      },
      {
        "id": 107,
        "x": 1358.4643765472592,
        "y": -435.95659278397295
      },
      {
        "id": 108,
        "x": 1421.6569100042157,
        "y": -560.8478239316366
      },
      {
        "id": 109,
        "x": 1964.428782174374,
        "y": -287.30034016976015
      },
      {
        "id": 1010,
        "x": 1364.1795244692962,
        "y": 787.5983955138046
      },
      {
        "id": 1011,
        "x": 1188.1765684156758,
        "y": 698.8960052431308
      },
      {
        "id": 1012,
        "x": 1110.8175111831265,
        "y": 659.9084005840675
      },
      {
        "id": 1013,
        "x": 934.814558231166,
        "y": 571.2060041591722
      },
      {
        "id": 1014,
        "x": 1497.8441011318396,
        "y": -522.4508179957741
      },
      {
        "id": 1015,
        "x": 1673.847054087421,
        "y": -433.7484215779267
      },
      {
        "id": 1016,
        "x": 1743.1888542722786,
        "y": -398.8013953609543
      },
      {
        "id": 1017,
        "x": 1919.1918014454852,
        "y": -310.0989874698393
      },
      {
        "id": 1018,
        "x": 1371.9497849862428,
        "y": -462.6086222301568
      },
      {
        "id": 1019,
        "x": 1421.6317518393266,
        "y": -560.7981023266541
      },
      {
        "id": 1020,
        "x": 1061.6922848743777,
        "y": -585.4887196157497
      },
      {
        "id": 1021,
        "x": 1327.260582547016,
        "y": -451.678993282535
      },
      {
        "id": 1022,
        "x": 1092.6884711180264,
        "y": 69.58541372788213
      },
      {
        "id": 1023,
        "x": 1136.3438174939279,
        "y": -17.0352648358592
      },
      {
        "id": 1024,
        "x": 1421.5676098769459,
        "y": -560.8928296270312
      },
      {
        "id": 1025,
        "x": 1358.42021989888,
        "y": -436.09081827082827
      },
      {
        "id": 1026,
        "x": 1061.991123916672,
        "y": -585.450122668961
      },
      {
        "id": 1027,
        "x": 1125.1529282552888,
        "y": -710.2806219991401
      },
      {
        "id": 1028,
        "x": 1160.5561382735154,
        "y": 684.9757948736675
      },
      {
        "id": 1029,
        "x": 1714.1365907130355,
        "y": -413.4432028912914
      },
      {
        "id": 1030,
        "x": 1736.4615942354044,
        "y": -402.1917933028922
      },
      {
        "id": 1031,
        "x": 1182.878409791629,
        "y": 696.2258266022507
      },
      {
        "id": 1032,
        "x": 1604.5462357160688,
        "y": 426.4049439583705
      },
      {
        "id": 1033,
        "x": 1376.728667989958,
        "y": 311.58889179133814
      },
      {
        "id": 1034,
        "x": 1387.98007757951,
        "y": 289.26388826953746
      },
      {
        "id": 1035,
        "x": 1615.802324932313,
        "y": 404.0822988862178
      },
      {
        "id": 1036,
        "x": 1405.86506675,
        "y": 198.227966444
      },
      {
        "id": 1037,
        "x": 1381.2182597607703,
        "y": 185.8064086863406
      },
      {
        "id": 1038,
        "x": 1412.7222085793885,
        "y": 123.29639989404991
      },
      {
        "id": 1039,
        "x": 1379.324004359182,
        "y": 106.46429169088806
      },
      {
        "id": 1040,
        "x": 1411.7280640087051,
        "y": 42.168281492301915
      },
      {
        "id": 1041,
        "x": 1469.7730732436771,
        "y": 71.421946470794
      },
      {
        "id": 1042,
        "x": 1492.4554772200001,
        "y": 82.0816334735
      },
      {
        "id": 1043,
        "x": 1540.6124593684563,
        "y": -13.45143625660744
      },
      {
        "id": 1044,
        "x": 1580.7912720332345,
        "y": 6.793613596312298
      },
      {
        "id": 1045,
        "x": 1532.6405039527801,
        "y": 102.33418117675869
      },
      {
        "id": 1046,
        "x": 1450.52117089,
        "y": 320.783500624
      },
      {
        "id": 1047,
        "x": 1387.9800775829162,
        "y": 289.26388826961977
      },
      {
        "id": 1048,
        "x": 1419.515107951904,
        "y": 226.76954388012564
      },
      {
        "id": 1049,
        "x": 1482.0251178033218,
        "y": 258.2734907654843
      }
    ]
  }
}