{
    "meta": {
        "cacheKey": "B2E4L02_0",
        "cells": [
            "X2E4C02"
        ],
        "projectSlug": "paris-venelles",
        "slug": "B2E4L02"
    },
    "v1": {
        "apartment": {
            "area": 672289,
            "blueprints": [
                {
                    "externalSpaces": [
                        {
                            "area": 45484.48397301889,
                            "polygon": [
                                [
                                    2215.3424942500005,
                                    -87.17985465880028
                                ],
                                [
                                    2249.1199176169675,
                                    -154.20098297105247
                                ],
                                [
                                    2788.4115685839524,
                                    117.59253526770415
                                ],
                                [
                                    2782.619018293074,
                                    129.53248925602472
                                ],
                                [
                                    2818.1972946698193,
                                    147.4633172600914
                                ],
                                [
                                    2772.709908393928,
                                    237.71921373769482
                                ],
                                [
                                    2228.4074961384945,
                                    -36.59964014038757
                                ],
                                [
                                    2246.0792482237653,
                                    -71.66433609325041
                                ]
                            ],
                            "type": "terrace",
                            "windows": [
                                1,
                                2
                            ]
                        }
                    ],
                    "externalWalls": [
                        0,
                        1,
                        2,
                        3,
                        4,
                        5,
                        6,
                        7,
                        8,
                        9
                    ],
                    "fixedItems": [
                        {
                            "coef1": 285,
                            "coef2": 619,
                            "sillHeight": 0,
                            "type": "doorWindow",
                            "vertex1": 5,
                            "vertex2": 6,
                            "width": 80
                        },
                        {
                            "coef1": 60,
                            "coef2": 382,
                            "sillHeight": 0,
                            "type": "doorWindow",
                            "vertex1": 7,
                            "vertex2": 8,
                            "width": 80
                        },
                        {
                            "coef1": 507,
                            "coef2": 828,
                            "sillHeight": 0,
                            "type": "doorWindow",
                            "vertex1": 7,
                            "vertex2": 8,
                            "width": 80
                        },
                        {
                            "coef1": 0,
                            "coef2": 998,
                            "sillHeight": 100,
                            "type": "window",
                            "vertex1": 9,
                            "vertex2": 0,
                            "width": 80
                        },
                        {
                            "coef1": 197,
                            "coef2": 386,
                            "type": "frontDoor",
                            "vertex1": 4,
                            "vertex2": 5,
                            "width": 90
                        },
                        {
                            "coef1": 206,
                            "coef2": 314,
                            "type": "duct",
                            "vertex1": 6,
                            "vertex2": 7,
                            "width": 56
                        },
                        {
                            "coef1": 48,
                            "coef2": 197,
                            "type": "duct",
                            "vertex1": 4,
                            "vertex2": 5,
                            "width": 65
                        }
                    ],
                    "forbiddenZones": [],
                    "level": 4,
                    "loadBearingWalls": [],
                    "rooms": [],
                    "unsplittableZones": [],
                    "vertices": [
                        {
                            "x": 3105,
                            "y": 292
                        },
                        {
                            "x": 2952,
                            "y": 596
                        },
                        {
                            "x": 2759,
                            "y": 499
                        },
                        {
                            "x": 2687,
                            "y": 642
                        },
                        {
                            "x": 2573,
                            "y": 584
                        },
                        {
                            "x": 2341,
                            "y": 1045
                        },
                        {
                            "x": 1817,
                            "y": 780
                        },
                        {
                            "x": 2228,
                            "y": -37
                        },
                        {
                            "x": 2773,
                            "y": 238
                        },
                        {
                            "x": 2818,
                            "y": 148
                        }
                    ]
                }
            ],
            "id": "B2E4L02",
            "ifcIds": [
                433340
            ],
            "levels": [
                4
            ],
            "north": [
                0.0,
                1.0
            ]
        }
    },
    "v2": {
        "aptInfos": {
            "north": [
                0.0,
                1.0
            ]
        },
        "floors": [
            {
                "elements": [
                    301,
                    201,
                    202,
                    203,
                    204,
                    205,
                    302,
                    303,
                    304
                ],
                "id": 401,
                "level": 4
            }
        ],
        "linears": [
            {
                "category": "doorWindow",
                "externalSpaces": [],
                "geometry": [
                    1011,
                    1012
                ],
                "id": 201,
                "length": 196.00000000012136,
                "sillHeight": 0
            },
            {
                "category": "doorWindow",
                "externalSpaces": [
                    302
                ],
                "geometry": [
                    1013,
                    1014
                ],
                "id": 202,
                "length": 195.9859999999779,
                "sillHeight": 0
            },
            {
                "category": "doorWindow",
                "externalSpaces": [
                    302
                ],
                "geometry": [
                    1015,
                    1016
                ],
                "id": 203,
                "length": 195.99999999997797,
                "sillHeight": 0
            },
            {
                "category": "window",
                "externalSpaces": [],
                "geometry": [
                    1017,
                    1018
                ],
                "id": 204,
                "length": 320.2429948397105,
                "sillHeight": 999.8999999999996
            },
            {
                "category": "frontDoor",
                "geometry": [
                    1019,
                    1020
                ],
                "id": 205,
                "length": 97.3528999999785
            }
        ],
        "spaces": [
            {
                "area": 672288.655731171,
                "category": "empty",
                "geometry": [
                    101,
                    102,
                    103,
                    104,
                    105,
                    106,
                    107,
                    108,
                    109,
                    1010
                ],
                "id": 301
            },
            {
                "area": 4548448.397301889,
                "category": "terrace",
                "geometry": [
                    1021,
                    1022,
                    1023,
                    1024,
                    1025,
                    1026,
                    1027,
                    1028
                ],
                "id": 302
            },
            {
                "area": 5512.462199978777,
                "category": "duct",
                "geometry": [
                    1029,
                    1030,
                    1031,
                    1032
                ],
                "id": 303
            },
            {
                "area": 4739.1985800774455,
                "category": "duct",
                "geometry": [
                    1033,
                    1034,
                    1035,
                    1036
                ],
                "id": 304
            }
        ],
        "vertices": [
            {
                "id": 101,
                "x": 3104.9594275906134,
                "y": 291.9864085148126
            },
            {
                "id": 102,
                "x": 2951.83125575874,
                "y": 595.7916560810876
            },
            {
                "id": 103,
                "x": 2759.216712772887,
                "y": 498.7173101244325
            },
            {
                "id": 104,
                "x": 2687.127321131688,
                "y": 641.623791070698
            },
            {
                "id": 105,
                "x": 2573.487163406022,
                "y": 584.3536318653823
            },
            {
                "id": 106,
                "x": 2341.4506795600005,
                "y": 1044.6985491700002
            },
            {
                "id": 107,
                "x": 1816.7345669849594,
                "y": 780.2512314166431
            },
            {
                "id": 108,
                "x": 2228.3624909968903,
                "y": -36.51033990580778
            },
            {
                "id": 109,
                "x": 2772.7542027696722,
                "y": 237.8535193901386
            },
            {
                "id": 1010,
                "x": 2818.2865946820048,
                "y": 147.5083229018008
            },
            {
                "id": 1011,
                "x": 2191.864132120829,
                "y": 969.3096668882177
            },
            {
                "id": 1012,
                "x": 2016.8360528633286,
                "y": 881.0987181829817
            },
            {
                "id": 1013,
                "x": 2261.254098814811,
                "y": -19.93354737899591
            },
            {
                "id": 1014,
                "x": 2436.2696244310832,
                "y": 68.27120299903834
            },
            {
                "id": 1015,
                "x": 2504.1501370969863,
                "y": 102.48178891217904
            },
            {
                "id": 1016,
                "x": 2679.178164715231,
                "y": 190.69284007958237
            },
            {
                "id": 1017,
                "x": 2818.2865946820048,
                "y": 147.50832290180097
            },
            {
                "id": 1018,
                "x": 3104.2636286400148,
                "y": 291.63573803329507
            },
            {
                "id": 1019,
                "x": 2527.757517930065,
                "y": 675.0782003300916
            },
            {
                "id": 1020,
                "x": 2483.9385957562945,
                "y": 762.0120211246178
            },
            {
                "id": 1021,
                "x": 2215.342494250001,
                "y": -87.17985465879984
            },
            {
                "id": 1022,
                "x": 2249.119917616968,
                "y": -154.20098297105227
            },
            {
                "id": 1023,
                "x": 2788.411568583956,
                "y": 117.59253526770605
            },
            {
                "id": 1024,
                "x": 2782.619018293072,
                "y": 129.5324892560242
            },
            {
                "id": 1025,
                "x": 2818.197294667912,
                "y": 147.46331726345406
            },
            {
                "id": 1026,
                "x": 2772.709908393928,
                "y": 237.7192137376947
            },
            {
                "id": 1027,
                "x": 2228.4074961504966,
                "y": -36.59964016420222
            },
            {
                "id": 1028,
                "x": 2246.0792482237644,
                "y": -71.66433609325068
            },
            {
                "id": 1029,
                "x": 1996.0277717699998,
                "y": 549.2698150899984
            },
            {
                "id": 1030,
                "x": 1951.8486829829112,
                "y": 636.9297926227798
            },
            {
                "id": 1031,
                "x": 1901.702062690198,
                "y": 611.6567769285926
            },
            {
                "id": 1032,
                "x": 1945.8814070100561,
                "y": 523.9951082670408
            },
            {
                "id": 1033,
                "x": 2527.755732823951,
                "y": 675.0817418616354
            },
            {
                "id": 1034,
                "x": 2472.77188078,
                "y": 647.4031242419996
            },
            {
                "id": 1035,
                "x": 2507.426211633191,
                "y": 578.642134577273
            },
            {
                "id": 1036,
                "x": 2562.400750334607,
                "y": 606.3483364220681
            }
        ]
    }
}