{
    "apartment": {
        "area": 664466,
        "blueprints": [
            {
                "externalSpaces": [
                    {
                        "area": 21900,
                        "type": "balcony",
                        "windows": [
                            0,
                            1
                        ]
                    }
                ],
                "externalWalls": [
                    0,
                    1,
                    2,
                    3,
                    4,
                    5
                ],
                "fixedItems": [
                    {
                        "coef1": 1,
                        "coef2": 109,
                        "type": "doorWindow",
                        "vertex1": 0,
                        "vertex2": 1,
                        "width": 25
                    },
                    {
                        "coef1": 148,
                        "coef2": 218,
                        "type": "window",
                        "vertex1": 0,
                        "vertex2": 1,
                        "width": 22
                    },
                    {
                        "coef1": 300,
                        "coef2": 370,
                        "type": "window",
                        "vertex1": 0,
                        "vertex2": 1,
                        "width": 15
                    },
                    {
                        "coef1": 512,
                        "coef2": 583,
                        "type": "window",
                        "vertex1": 0,
                        "vertex2": 1,
                        "width": 11
                    },
                    {
                        "coef1": 674,
                        "coef2": 745,
                        "type": "window",
                        "vertex1": 0,
                        "vertex2": 1,
                        "width": 12
                    },
                    {
                        "coef1": 842,
                        "coef2": 912,
                        "type": "window",
                        "vertex1": 0,
                        "vertex2": 1,
                        "width": 13
                    },
                    {
                        "coef1": 409,
                        "coef2": 541,
                        "type": "duct",
                        "vertex1": 3,
                        "vertex2": 4,
                        "width": 70
                    },
                    {
                        "coef1": 0,
                        "coef2": 1000,
                        "type": "duct",
                        "vertex1": 6,
                        "vertex2": 7,
                        "width": 66
                    },
                    {
                        "coef1": 452,
                        "coef2": 525,
                        "type": "frontDoor",
                        "vertex1": 4,
                        "vertex2": 5,
                        "width": 92
                    }
                ],
                "forbiddenZones": [],
                "level": 0,
                "loadBearingWalls": [],
                "unsplittableZones": [],
                "vertices": [
                    {
                        "x": 0,
                        "y": 0
                    },
                    {
                        "x": 1298,
                        "y": 0
                    },
                    {
                        "x": 1298,
                        "y": 145
                    },
                    {
                        "x": 1312,
                        "y": 145
                    },
                    {
                        "x": 1312,
                        "y": 508
                    },
                    {
                        "x": 0,
                        "y": 508
                    },
                    {
                        "x": 645,
                        "y": 215
                    },
                    {
                        "x": 645,
                        "y": 255
                    }
                ]
            }
        ],
        "id": "Vernouillet_A105",
        "levels": [
            0
        ],
        "north": [
            1,
            0
        ]
    }
}